{"paths": {"admin/js/vendor/select2/i18n/pt.js": "admin/js/vendor/select2/i18n/pt.33b4a3b44d43.js", "admin/js/vendor/select2/i18n/hsb.js": "admin/js/vendor/select2/i18n/hsb.fa3b55265efe.js", "admin/js/vendor/select2/i18n/vi.js": "admin/js/vendor/select2/i18n/vi.097a5b75b3e1.js", "admin/js/vendor/select2/i18n/lv.js": "admin/js/vendor/select2/i18n/lv.08e62128eac1.js", "admin/js/vendor/select2/i18n/gl.js": "admin/js/vendor/select2/i18n/gl.d99b1fedaa86.js", "admin/js/vendor/select2/i18n/pl.js": "admin/js/vendor/select2/i18n/pl.6031b4f16452.js", "admin/js/vendor/select2/i18n/el.js": "admin/js/vendor/select2/i18n/el.27097f071856.js", "admin/js/vendor/select2/i18n/dsb.js": "admin/js/vendor/select2/i18n/dsb.56372c92d2f1.js", "admin/js/vendor/select2/i18n/et.js": "admin/js/vendor/select2/i18n/et.2b96fd98289d.js", "admin/js/vendor/select2/i18n/is.js": "admin/js/vendor/select2/i18n/is.3ddd9a6a97e9.js", "admin/js/vendor/select2/i18n/sl.js": "admin/js/vendor/select2/i18n/sl.131a78bc0752.js", "admin/js/vendor/select2/i18n/ko.js": "admin/js/vendor/select2/i18n/ko.e7be6c20e673.js", "admin/js/vendor/select2/i18n/hr.js": "admin/js/vendor/select2/i18n/hr.a2b092cc1147.js", "admin/js/vendor/select2/i18n/ms.js": "admin/js/vendor/select2/i18n/ms.4ba82c9a51ce.js", "admin/js/vendor/select2/i18n/fi.js": "admin/js/vendor/select2/i18n/fi.614ec42aa9ba.js", "admin/js/vendor/select2/i18n/th.js": "admin/js/vendor/select2/i18n/th.f38c20b0221b.js", "admin/js/vendor/select2/i18n/ru.js": "admin/js/vendor/select2/i18n/ru.934aa95f5b5f.js", "admin/js/vendor/select2/i18n/eu.js": "admin/js/vendor/select2/i18n/eu.adfe5c97b72c.js", "admin/js/vendor/select2/i18n/mk.js": "admin/js/vendor/select2/i18n/mk.dabbb9087130.js", "admin/js/vendor/select2/i18n/sq.js": "admin/js/vendor/select2/i18n/sq.5636b60d29c9.js", "admin/js/vendor/select2/i18n/ja.js": "admin/js/vendor/select2/i18n/ja.170ae885d74f.js", "admin/js/vendor/select2/i18n/ka.js": "admin/js/vendor/select2/i18n/ka.2083264a54f0.js", "admin/js/vendor/select2/i18n/he.js": "admin/js/vendor/select2/i18n/he.e420ff6cd3ed.js", "admin/js/vendor/select2/i18n/bg.js": "admin/js/vendor/select2/i18n/bg.39b8be30d4f0.js", "admin/js/vendor/select2/i18n/hy.js": "admin/js/vendor/select2/i18n/hy.c7babaeef5a6.js", "admin/js/vendor/select2/i18n/sr-Cyrl.js": "admin/js/vendor/select2/i18n/sr-Cyrl.f254bb8c4c7c.js", "admin/js/vendor/select2/i18n/ne.js": "admin/js/vendor/select2/i18n/ne.3d79fd3f08db.js", "admin/js/vendor/select2/i18n/af.js": "admin/js/vendor/select2/i18n/af.4f6fcd73488c.js", "admin/js/vendor/select2/i18n/id.js": "admin/js/vendor/select2/i18n/id.04debded514d.js", "admin/js/vendor/select2/i18n/az.js": "admin/js/vendor/select2/i18n/az.270c257daf81.js", "admin/js/vendor/select2/i18n/ca.js": "admin/js/vendor/select2/i18n/ca.a166b745933a.js", "admin/js/vendor/select2/i18n/nb.js": "admin/js/vendor/select2/i18n/nb.da2fce143f27.js", "admin/js/vendor/select2/i18n/zh-CN.js": "admin/js/vendor/select2/i18n/zh-CN.2cff662ec5f9.js", "admin/js/vendor/select2/i18n/zh-TW.js": "admin/js/vendor/select2/i18n/zh-TW.04554a227c2b.js", "admin/js/vendor/select2/i18n/pt-BR.js": "admin/js/vendor/select2/i18n/pt-BR.e1b294433e7f.js", "admin/js/vendor/select2/i18n/da.js": "admin/js/vendor/select2/i18n/da.766346afe4dd.js", "admin/js/vendor/select2/i18n/fa.js": "admin/js/vendor/select2/i18n/fa.3b5bd1961cfd.js", "admin/js/vendor/select2/i18n/de.js": "admin/js/vendor/select2/i18n/de.8a1c222b0204.js", "admin/js/vendor/select2/i18n/en.js": "admin/js/vendor/select2/i18n/en.cf932ba09a98.js", "admin/js/vendor/select2/i18n/bs.js": "admin/js/vendor/select2/i18n/bs.91624382358e.js", "admin/js/vendor/select2/i18n/tk.js": "admin/js/vendor/select2/i18n/tk.7c572a68c78f.js", "admin/js/vendor/select2/i18n/sv.js": "admin/js/vendor/select2/i18n/sv.7a9c2f71e777.js", "admin/js/vendor/select2/i18n/hi.js": "admin/js/vendor/select2/i18n/hi.70640d41628f.js", "admin/js/vendor/select2/i18n/uk.js": "admin/js/vendor/select2/i18n/uk.8cede7f4803c.js", "admin/js/vendor/select2/i18n/cs.js": "admin/js/vendor/select2/i18n/cs.4f43e8e7d33a.js", "admin/js/vendor/select2/i18n/km.js": "admin/js/vendor/select2/i18n/km.c23089cb06ca.js", "admin/js/vendor/select2/i18n/fr.js": "admin/js/vendor/select2/i18n/fr.05e0542fcfe6.js", "admin/js/vendor/select2/i18n/nl.js": "admin/js/vendor/select2/i18n/nl.997868a37ed8.js", "admin/js/vendor/select2/i18n/sr.js": "admin/js/vendor/select2/i18n/sr.5ed85a48f483.js", "admin/js/vendor/select2/i18n/hu.js": "admin/js/vendor/select2/i18n/hu.6ec6039cb8a3.js", "admin/js/vendor/select2/i18n/lt.js": "admin/js/vendor/select2/i18n/lt.23c7ce903300.js", "admin/js/vendor/select2/i18n/ar.js": "admin/js/vendor/select2/i18n/ar.65aa8e36bf5d.js", "admin/js/vendor/select2/i18n/sk.js": "admin/js/vendor/select2/i18n/sk.33d02cef8d11.js", "admin/js/vendor/select2/i18n/it.js": "admin/js/vendor/select2/i18n/it.be4fe8d365b5.js", "admin/js/vendor/select2/i18n/es.js": "admin/js/vendor/select2/i18n/es.66dbc2652fb1.js", "admin/js/vendor/select2/i18n/bn.js": "admin/js/vendor/select2/i18n/bn.6d42b4dd5665.js", "admin/js/vendor/select2/i18n/ro.js": "admin/js/vendor/select2/i18n/ro.f75cb460ec3b.js", "admin/js/vendor/select2/i18n/ps.js": "admin/js/vendor/select2/i18n/ps.38dfa47af9e0.js", "admin/js/vendor/select2/i18n/tr.js": "admin/js/vendor/select2/i18n/tr.b5a0643d1545.js", "blockly/core/renderers/zelos/measurables/rows.js": "blockly/core/renderers/zelos/measurables/rows.db74a72e2b4a.js", "blockly/core/renderers/zelos/measurables/row_elements.js": "blockly/core/renderers/zelos/measurables/row_elements.3ed8267f6590.js", "blockly/core/renderers/zelos/measurables/inputs.js": "blockly/core/renderers/zelos/measurables/inputs.7960582cc448.js", "blockly/core/renderers/geras/measurables/inputs.js": "blockly/core/renderers/geras/measurables/inputs.a2dcf30027eb.js", "admin/css/vendor/select2/select2.min.css": "admin/css/vendor/select2/select2.min.9f54e6414f87.css", "admin/css/vendor/select2/LICENSE-SELECT2.md": "admin/css/vendor/select2/LICENSE-SELECT2.f94142512c91.md", "admin/css/vendor/select2/select2.css": "admin/css/vendor/select2/select2.a2194c262648.css", "admin/js/vendor/jquery/jquery.min.js": "admin/js/vendor/jquery/jquery.min.dc5e7f18c8d3.js", "admin/js/vendor/jquery/LICENSE.txt": "admin/js/vendor/jquery/LICENSE.75308107741f.txt", "admin/js/vendor/jquery/jquery.js": "admin/js/vendor/jquery/jquery.23c7c5d2d131.js", "admin/js/vendor/xregexp/xregexp.min.js": "admin/js/vendor/xregexp/xregexp.min.b0439563a5d3.js", "admin/js/vendor/xregexp/xregexp.js": "admin/js/vendor/xregexp/xregexp.efda034b9537.js", "admin/js/vendor/xregexp/LICENSE.txt": "admin/js/vendor/xregexp/LICENSE.bf79e414957a.txt", "admin/js/vendor/select2/LICENSE.md": "admin/js/vendor/select2/LICENSE.f94142512c91.md", "admin/js/vendor/select2/select2.full.min.js": "admin/js/vendor/select2/select2.full.min.fcd7500d8e13.js", "admin/js/vendor/select2/select2.full.js": "admin/js/vendor/select2/select2.full.c2afdeda3058.js", "blockly/core/renderers/thrasos/renderer.js": "blockly/core/renderers/thrasos/renderer.acb45e45ff92.js", "blockly/core/renderers/thrasos/info.js": "blockly/core/renderers/thrasos/info.29c2652614c3.js", "blockly/core/renderers/common/constants.js": "blockly/core/renderers/common/constants.0f8ada4e07c0.js", "blockly/core/renderers/common/i_path_object.js": "blockly/core/renderers/common/i_path_object.40d71cbe177b.js", "blockly/core/renderers/common/renderer.js": "blockly/core/renderers/common/renderer.db6acf70f0e1.js", "blockly/core/renderers/common/path_object.js": "blockly/core/renderers/common/path_object.d5ef172f3ec4.js", "blockly/core/renderers/common/marker_svg.js": "blockly/core/renderers/common/marker_svg.b58de73a2a1b.js", "blockly/core/renderers/common/drawer.js": "blockly/core/renderers/common/drawer.3929853f8aec.js", "blockly/core/renderers/common/info.js": "blockly/core/renderers/common/info.84791ece358d.js", "blockly/core/renderers/common/test_marker_svg.js": "blockly/core/renderers/common/test_marker_svg.d41d8cd98f00.js", "blockly/core/renderers/common/debugger.js": "blockly/core/renderers/common/debugger.416062dd0a34.js", "blockly/core/renderers/common/block_rendering.js": "blockly/core/renderers/common/block_rendering.f9408c94ad2a.js", "blockly/core/renderers/measurables/connections.js": "blockly/core/renderers/measurables/connections.83ec9c41c7ce.js", "blockly/core/renderers/measurables/types.js": "blockly/core/renderers/measurables/types.384e5d493d26.js", "blockly/core/renderers/measurables/rows.js": "blockly/core/renderers/measurables/rows.a0242a158266.js", "blockly/core/renderers/measurables/row_elements.js": "blockly/core/renderers/measurables/row_elements.b05b15d34aba.js", "blockly/core/renderers/measurables/base.js": "blockly/core/renderers/measurables/base.aa9d95f9b12d.js", "blockly/core/renderers/measurables/inputs.js": "blockly/core/renderers/measurables/inputs.185d623b1c07.js", "blockly/core/renderers/zelos/constants.js": "blockly/core/renderers/zelos/constants.4d05b3363751.js", "blockly/core/renderers/zelos/renderer.js": "blockly/core/renderers/zelos/renderer.8f32b383a59e.js", "blockly/core/renderers/zelos/path_object.js": "blockly/core/renderers/zelos/path_object.775bab42eadf.js", "blockly/core/renderers/zelos/marker_svg.js": "blockly/core/renderers/zelos/marker_svg.56a8d92b3cf0.js", "blockly/core/renderers/zelos/drawer.js": "blockly/core/renderers/zelos/drawer.305122abfbba.js", "blockly/core/renderers/zelos/info.js": "blockly/core/renderers/zelos/info.0a9adb58282a.js", "blockly/core/renderers/minimalist/constants.js": "blockly/core/renderers/minimalist/constants.3cd43262661c.js", "blockly/core/renderers/minimalist/renderer.js": "blockly/core/renderers/minimalist/renderer.bd60fa1edb71.js", "blockly/core/renderers/minimalist/drawer.js": "blockly/core/renderers/minimalist/drawer.47d9f202bfc5.js", "blockly/core/renderers/minimalist/info.js": "blockly/core/renderers/minimalist/info.e5c1cf46df92.js", "blockly/core/renderers/geras/constants.js": "blockly/core/renderers/geras/constants.8a180bcb89c2.js", "blockly/core/renderers/geras/renderer.js": "blockly/core/renderers/geras/renderer.bddf8f6834e3.js", "blockly/core/renderers/geras/path_object.js": "blockly/core/renderers/geras/path_object.e702793a845f.js", "blockly/core/renderers/geras/drawer.js": "blockly/core/renderers/geras/drawer.0c637e80af08.js", "blockly/core/renderers/geras/info.js": "blockly/core/renderers/geras/info.01cf1da02a8b.js", "blockly/core/renderers/geras/highlight_constants.js": "blockly/core/renderers/geras/highlight_constants.e2df312b4fac.js", "blockly/core/renderers/geras/highlighter.js": "blockly/core/renderers/geras/highlighter.1869b7738744.js", "js/game_views/three/three.js": "js/game_views/three/three.0ce6ebe32b46.js", "js/game_views/three/orbit_controls.js": "js/game_views/three/orbit_controls.ad5402bd8166.js", "admin/js/admin/RelatedObjectLookups.js": "admin/js/admin/RelatedObjectLookups.b4d76b6aaf0b.js", "admin/js/admin/DateTimeShortcuts.js": "admin/js/admin/DateTimeShortcuts.5548f99471bf.js", "admin/img/gis/move_vertex_on.svg": "admin/img/gis/move_vertex_on.0047eba25b67.svg", "admin/img/gis/move_vertex_off.svg": "admin/img/gis/move_vertex_off.7a23bf31ef8a.svg", "3d_assets/players/0/model.json": "3d_assets/players/0/model.d8fd37af66d3.json", "3d_assets/players/0/marioD.jpg": "3d_assets/players/0/marioD.de3d67729964.jpg", "3d_assets/players/1/model.json": "3d_assets/players/1/model.685eb186e065.json", "3d_assets/players/3/model.json": "3d_assets/players/3/model.7f62c4188e9d.json", "3d_assets/players/3/RobotSurface_Color.png": "3d_assets/players/3/RobotSurface_Color.3c40c673ea66.png", "3d_assets/players/3/ReyeSurface_Color.png": "3d_assets/players/3/ReyeSurface_Color.5d4ff911d0fd.png", "3d_assets/players/3/LeyeSurface_Color.png": "3d_assets/players/3/LeyeSurface_Color.3308dd2be800.png", "3d_assets/players/3/Name_PlateSurface_Color.png": "3d_assets/players/3/Name_PlateSurface_Color.20ac780428c1.png", "3d_assets/players/2/model.json": "3d_assets/players/2/model.a6e9a3efc48f.json", "3d_assets/players/2/R2D2_Normal.jpg": "3d_assets/players/2/R2D2_Normal.2f8ee0d7d8b0.jpg", "3d_assets/players/2/R2D2_Illumination.jpg": "3d_assets/players/2/R2D2_Illumination.669cf3d6869a.jpg", "3d_assets/players/2/R2D2_Specular.jpg": "3d_assets/players/2/R2D2_Specular.4c4d5f67aa06.jpg", "3d_assets/players/2/R2D2_Diffuse.jpg": "3d_assets/players/2/R2D2_Diffuse.604c5ff1658e.jpg", "3d_assets/players/2/R2D2_Reflection.jpg": "3d_assets/players/2/R2D2_Reflection.63597341041a.jpg", "blockly/core/utils/deprecation.js": "blockly/core/utils/deprecation.2e3fca3ffe00.js", "blockly/core/utils/rect.js": "blockly/core/utils/rect.43540552933a.js", "blockly/core/utils/size.js": "blockly/core/utils/size.ee2c98b4f7fc.js", "blockly/core/utils/coordinate.js": "blockly/core/utils/coordinate.c8dff0fe443e.js", "blockly/core/utils/xml.js": "blockly/core/utils/xml.eca744289217.js", "blockly/core/utils/svg_paths.js": "blockly/core/utils/svg_paths.65e6d095ad9c.js", "blockly/core/utils/metrics.js": "blockly/core/utils/metrics.88123a6f5973.js", "blockly/core/utils/aria.js": "blockly/core/utils/aria.852d6c94ee41.js", "blockly/core/utils/object.js": "blockly/core/utils/object.b85bdeb09069.js", "blockly/core/utils/global.js": "blockly/core/utils/global.7efb6d1cfd9f.js", "blockly/core/utils/toolbox.js": "blockly/core/utils/toolbox.b9834727d431.js", "blockly/core/utils/style.js": "blockly/core/utils/style.2af1316f3b43.js", "blockly/core/utils/useragent.js": "blockly/core/utils/useragent.eb7b97dc326f.js", "blockly/core/utils/string.js": "blockly/core/utils/string.675b7a74cd69.js", "blockly/core/utils/math.js": "blockly/core/utils/math.41a4dd1c921d.js", "blockly/core/utils/dom.js": "blockly/core/utils/dom.e7ede08bdad1.js", "blockly/core/utils/colour.js": "blockly/core/utils/colour.dae66a90b9b0.js", "blockly/core/utils/svg.js": "blockly/core/utils/svg.2024f79502a2.js", "blockly/core/utils/idgenerator.js": "blockly/core/utils/idgenerator.ed55d861b1fe.js", "blockly/core/utils/keycodes.js": "blockly/core/utils/keycodes.88d4edadeb27.js", "blockly/core/keyboard_nav/basic_cursor.js": "blockly/core/keyboard_nav/basic_cursor.02604132baea.js", "blockly/core/keyboard_nav/tab_navigate_cursor.js": "blockly/core/keyboard_nav/tab_navigate_cursor.2945928360e8.js", "blockly/core/keyboard_nav/navigation.js": "blockly/core/keyboard_nav/navigation.51801aa3be7b.js", "blockly/core/keyboard_nav/ast_node.js": "blockly/core/keyboard_nav/ast_node.e76f9a263d8a.js", "blockly/core/keyboard_nav/cursor.js": "blockly/core/keyboard_nav/cursor.81795bcb6cd2.js", "blockly/core/keyboard_nav/flyout_cursor.js": "blockly/core/keyboard_nav/flyout_cursor.3f69bf8cdc4f.js", "blockly/core/keyboard_nav/marker.js": "blockly/core/keyboard_nav/marker.2976fe629866.js", "blockly/core/theme/zelos.js": "blockly/core/theme/zelos.0498732dde32.js", "blockly/core/theme/highcontrast.js": "blockly/core/theme/highcontrast.b3dd9afb0f64.js", "blockly/core/theme/tritanopia.js": "blockly/core/theme/tritanopia.8c961c3469f4.js", "blockly/core/theme/modern.js": "blockly/core/theme/modern.c063b231c635.js", "blockly/core/theme/dark.js": "blockly/core/theme/dark.23973a1b4798.js", "blockly/core/theme/classic.js": "blockly/core/theme/classic.4c78fc52c34e.js", "blockly/core/theme/deuteranopia.js": "blockly/core/theme/deuteranopia.a7615092edcb.js", "blockly/core/toolbox/separator.js": "blockly/core/toolbox/separator.e23553525afd.js", "blockly/core/toolbox/toolbox.js": "blockly/core/toolbox/toolbox.0f0ea8c9fec1.js", "blockly/core/toolbox/collapsible_category.js": "blockly/core/toolbox/collapsible_category.5469222fb74b.js", "blockly/core/toolbox/category.js": "blockly/core/toolbox/category.555707ffe076.js", "blockly/core/toolbox/toolbox_item.js": "blockly/core/toolbox/toolbox_item.ab6c3ce7aef4.js", "blockly/core/events/events.js": "blockly/core/events/events.097aa3b577ef.js", "blockly/core/events/events_viewport.js": "blockly/core/events/events_viewport.d4bf60fb31f9.js", "blockly/core/events/variable_events.js": "blockly/core/events/variable_events.61a0f455da99.js", "blockly/core/events/block_events.js": "blockly/core/events/block_events.354a26a4d722.js", "blockly/core/events/events_marker_move.js": "blockly/core/events/events_marker_move.d67550e4cf79.js", "blockly/core/events/events_theme_change.js": "blockly/core/events/events_theme_change.49928ed3e314.js", "blockly/core/events/events_selected.js": "blockly/core/events/events_selected.a91f170d0ded.js", "blockly/core/events/workspace_events.js": "blockly/core/events/workspace_events.d0834f12d9c3.js", "blockly/core/events/events_bubble_open.js": "blockly/core/events/events_bubble_open.9a36ae4f37ac.js", "blockly/core/events/ws_comment_events.js": "blockly/core/events/ws_comment_events.174ee87c3bbe.js", "blockly/core/events/events_abstract.js": "blockly/core/events/events_abstract.74baab962f34.js", "blockly/core/events/events_block_drag.js": "blockly/core/events/events_block_drag.573f3ac6b76a.js", "blockly/core/events/events_toolbox_item_select.js": "blockly/core/events/events_toolbox_item_select.043a4d36883f.js", "blockly/core/events/events_click.js": "blockly/core/events/events_click.53b33811467f.js", "blockly/core/events/ui_events.js": "blockly/core/events/ui_events.f5dd8e7d5a7f.js", "blockly/core/events/events_trashcan_open.js": "blockly/core/events/events_trashcan_open.89401a22ef29.js", "blockly/core/interfaces/i_bubble.js": "blockly/core/interfaces/i_bubble.42ad918401e1.js", "blockly/core/interfaces/i_plugin.js": "blockly/core/interfaces/i_plugin.95bf254d4142.js", "blockly/core/interfaces/i_draggable.js": "blockly/core/interfaces/i_draggable.8665bd3e3bfc.js", "blockly/core/interfaces/i_selectable.js": "blockly/core/interfaces/i_selectable.94dd71a4a4c7.js", "blockly/core/interfaces/i_positionable.js": "blockly/core/interfaces/i_positionable.a431c4bda0c8.js", "blockly/core/interfaces/i_accessibility.js": "blockly/core/interfaces/i_accessibility.c7646bf8960f.js", "blockly/core/interfaces/i_toolbox.js": "blockly/core/interfaces/i_toolbox.855c16e46cc7.js", "blockly/core/interfaces/i_flyout.js": "blockly/core/interfaces/i_flyout.0906aa1b91f3.js", "blockly/core/interfaces/i_block_dragger.js": "blockly/core/interfaces/i_block_dragger.d18e6f0b1552.js", "blockly/core/interfaces/i_toolbox_item.js": "blockly/core/interfaces/i_toolbox_item.250d560d67a2.js", "blockly/core/interfaces/i_registrable.js": "blockly/core/interfaces/i_registrable.4a5c425a81d8.js", "blockly/core/interfaces/i_delete_area.js": "blockly/core/interfaces/i_delete_area.55c75a86bba6.js", "blockly/core/interfaces/i_movable.js": "blockly/core/interfaces/i_movable.04508e72196a.js", "blockly/core/interfaces/i_deletearea.js": "blockly/core/interfaces/i_deletearea.5c68a347455f.js", "blockly/core/interfaces/i_workspace_plugin.js": "blockly/core/interfaces/i_workspace_plugin.1533e69f03d3.js", "blockly/core/interfaces/i_deletable.js": "blockly/core/interfaces/i_deletable.1720e57a9138.js", "blockly/core/interfaces/i_metrics_manager.js": "blockly/core/interfaces/i_metrics_manager.484ebdb7cc6b.js", "blockly/core/interfaces/i_styleable.js": "blockly/core/interfaces/i_styleable.7464c874fe26.js", "blockly/core/interfaces/i_registrable_field.js": "blockly/core/interfaces/i_registrable_field.d313499208d3.js", "blockly/core/interfaces/i_drag_target.js": "blockly/core/interfaces/i_drag_target.9ff7ed7d0e3a.js", "blockly/core/interfaces/i_component.js": "blockly/core/interfaces/i_component.06cef148cc87.js", "blockly/core/interfaces/i_copyable.js": "blockly/core/interfaces/i_copyable.09a6011ed441.js", "blockly/core/interfaces/i_connection_checker.js": "blockly/core/interfaces/i_connection_checker.7579635516fa.js", "blockly/core/interfaces/i_contextmenu.js": "blockly/core/interfaces/i_contextmenu.38f7bf258edf.js", "blockly/core/interfaces/i_autohideable.js": "blockly/core/interfaces/i_autohideable.b4f3a19b28ea.js", "blockly/core/interfaces/i_block_drag_surface.js": "blockly/core/interfaces/i_block_drag_surface.95a7b972b4f0.js", "blockly/core/interfaces/i_bounded_element.js": "blockly/core/interfaces/i_bounded_element.ea2067cba652.js", "blockly/generators/python/variables.js": "blockly/generators/python/variables.b930335b75f0.js", "blockly/generators/python/logic.js": "blockly/generators/python/logic.fe7063b0a488.js", "blockly/generators/python/lists.js": "blockly/generators/python/lists.de167a8207d9.js", "blockly/generators/python/variables_dynamic.js": "blockly/generators/python/variables_dynamic.7235e0a932e1.js", "blockly/generators/python/procedures.js": "blockly/generators/python/procedures.74d7fcab4441.js", "blockly/generators/python/math.js": "blockly/generators/python/math.5cd71419ce93.js", "blockly/generators/python/colour.js": "blockly/generators/python/colour.64225514f93e.js", "blockly/generators/python/loops.js": "blockly/generators/python/loops.7d870a092bf2.js", "blockly/generators/python/text.js": "blockly/generators/python/text.80672688d0ae.js", "blockly/generators/dart/variables.js": "blockly/generators/dart/variables.172613e34f77.js", "blockly/generators/dart/logic.js": "blockly/generators/dart/logic.1c9c7344b681.js", "blockly/generators/dart/lists.js": "blockly/generators/dart/lists.e3ef8368d061.js", "blockly/generators/dart/variables_dynamic.js": "blockly/generators/dart/variables_dynamic.75d4c71d3c68.js", "blockly/generators/dart/procedures.js": "blockly/generators/dart/procedures.8dd38afbdd1b.js", "blockly/generators/dart/math.js": "blockly/generators/dart/math.79d6034973d5.js", "blockly/generators/dart/colour.js": "blockly/generators/dart/colour.66d446e98dae.js", "blockly/generators/dart/loops.js": "blockly/generators/dart/loops.f495cb1ebe06.js", "blockly/generators/dart/text.js": "blockly/generators/dart/text.8dadbd54cfb4.js", "blockly/generators/php/variables.js": "blockly/generators/php/variables.2e192bdb46f9.js", "blockly/generators/php/logic.js": "blockly/generators/php/logic.b48c9fca6048.js", "blockly/generators/php/lists.js": "blockly/generators/php/lists.5786b45e2133.js", "blockly/generators/php/variables_dynamic.js": "blockly/generators/php/variables_dynamic.82be548b3e02.js", "blockly/generators/php/procedures.js": "blockly/generators/php/procedures.415866b6a3d7.js", "blockly/generators/php/math.js": "blockly/generators/php/math.3bdddd73318e.js", "blockly/generators/php/colour.js": "blockly/generators/php/colour.83f6a43fe245.js", "blockly/generators/php/loops.js": "blockly/generators/php/loops.1b25dcbf6ae1.js", "blockly/generators/php/text.js": "blockly/generators/php/text.a1adbc75269e.js", "blockly/generators/lua/variables.js": "blockly/generators/lua/variables.37a27d5f756e.js", "blockly/generators/lua/logic.js": "blockly/generators/lua/logic.09e97c70b5e6.js", "blockly/generators/lua/lists.js": "blockly/generators/lua/lists.6692695b5880.js", "blockly/generators/lua/variables_dynamic.js": "blockly/generators/lua/variables_dynamic.70792475436c.js", "blockly/generators/lua/procedures.js": "blockly/generators/lua/procedures.a50b73a8ab66.js", "blockly/generators/lua/math.js": "blockly/generators/lua/math.e2b4182c3dd0.js", "blockly/generators/lua/colour.js": "blockly/generators/lua/colour.bf06a2344f36.js", "blockly/generators/lua/loops.js": "blockly/generators/lua/loops.9c08bde3fad1.js", "blockly/generators/lua/text.js": "blockly/generators/lua/text.12aa767a44e0.js", "blockly/generators/javascript/test_blocks.js": "blockly/generators/javascript/test_blocks.41dc25e28fd0.js", "blockly/generators/javascript/variables.js": "blockly/generators/javascript/variables.5f4fa746ff68.js", "blockly/generators/javascript/logic.js": "blockly/generators/javascript/logic.6e8a36d687cb.js", "blockly/generators/javascript/lists.js": "blockly/generators/javascript/lists.208310dada0f.js", "blockly/generators/javascript/variables_dynamic.js": "blockly/generators/javascript/variables_dynamic.ba461fbe39e1.js", "blockly/generators/javascript/procedures.js": "blockly/generators/javascript/procedures.f451fed8a2b9.js", "blockly/generators/javascript/math.js": "blockly/generators/javascript/math.8b3835be1f15.js", "blockly/generators/javascript/colour.js": "blockly/generators/javascript/colour.9f3cf7e0aa76.js", "blockly/generators/javascript/loops.js": "blockly/generators/javascript/loops.da23d7f18c59.js", "blockly/generators/javascript/text.js": "blockly/generators/javascript/text.7320c4386639.js", "js/creator/map_rule.js": "js/creator/map_rule.0a503e9dc095.js", "js/creator/score_board.js": "js/creator/score_board.b4fe71c30845.js", "js/creator/blockly_storage.js": "js/creator/blockly_storage.fc110582bbc1.js", "js/creator/map_detail.js": "js/creator/map_detail.c647f47ecec0.js", "js/creator/card_create.js": "js/creator/card_create.bb289958c689.js", "js/utils/audio_manager.js": "js/utils/audio_manager.18316be19ffb.js", "js/utils/audio_manager_score_board.js": "js/utils/audio_manager_score_board.88549d317991.js", "js/game_views/game_controller.js": "js/game_views/game_controller.50d8998094d7.js", "js/game_views/board.js": "js/game_views/board.7bfcdc227a83.js", "js/game_views/property_manager.js": "js/game_views/property_manager.430f7df9664a.js", "js/game_views/board_controller.js": "js/game_views/board_controller.fd60ff5b5605.js", "js/game_views/player.js": "js/game_views/player.84baaee87599.js", "js/views/profile.js": "js/views/profile.2c30dae8b152.js", "js/views/game.js": "js/views/game.4d25ac2c459d.js", "js/views/join.js": "js/views/join.ff76901720d3.js", "admin/css/widgets.css": "admin/css/widgets.694d845b2cb1.css", "admin/css/login.css": "admin/css/login.c35adf41bb6e.css", "admin/css/dashboard.css": "admin/css/dashboard.be83f13e4369.css", "admin/css/nav_sidebar.css": "admin/css/nav_sidebar.0fd434145f4d.css", "admin/css/responsive.css": "admin/css/responsive.b128bdf0edef.css", "admin/css/autocomplete.css": "admin/css/autocomplete.4a81fc4242d0.css", "admin/css/responsive_rtl.css": "admin/css/responsive_rtl.e13ae754cceb.css", "admin/css/forms.css": "admin/css/forms.1d89ec6432f5.css", "admin/css/fonts.css": "admin/css/fonts.168bab448fee.css", "admin/css/rtl.css": "admin/css/rtl.4bc23eb90919.css", "admin/css/base.css": "admin/css/base.1f418065fc2c.css", "admin/css/changelists.css": "admin/css/changelists.c70d77c47e69.css", "admin/js/urlify.js": "admin/js/urlify.25cc3eac8123.js", "admin/js/core.js": "admin/js/core.ccd84108ec57.js", "admin/js/collapse.js": "admin/js/collapse.f84e7410290f.js", "admin/js/actions.js": "admin/js/actions.a6d23e8853fd.js", "admin/js/prepopulate.js": "admin/js/prepopulate.bd2361dfd64d.js", "admin/js/cancel.js": "admin/js/cancel.ecc4c5ca7b32.js", "admin/js/nav_sidebar.js": "admin/js/nav_sidebar.7605597ddf52.js", "admin/js/autocomplete.js": "admin/js/autocomplete.b6b77d0e5906.js", "admin/js/inlines.js": "admin/js/inlines.7596b7fd289e.js", "admin/js/change_form.js": "admin/js/change_form.9d8ca4f96b75.js", "admin/js/SelectFilter2.js": "admin/js/SelectFilter2.d250dcb52a9a.js", "admin/js/jquery.init.js": "admin/js/jquery.init.b7781a0897fc.js", "admin/js/popup_response.js": "admin/js/popup_response.c6cc78ea5551.js", "admin/js/SelectBox.js": "admin/js/SelectBox.8161741c7647.js", "admin/js/calendar.js": "admin/js/calendar.f8a5d055eb33.js", "admin/js/prepopulate_init.js": "admin/js/prepopulate_init.e056047b7a7e.js", "admin/img/search.svg": "admin/img/search.7cf54ff789c6.svg", "admin/img/icon-calendar.svg": "admin/img/icon-calendar.ac7aea671bea.svg", "admin/img/icon-clock.svg": "admin/img/icon-clock.e1d4dfac3f2b.svg", "admin/img/icon-no.svg": "admin/img/icon-no.439e821418cd.svg", "admin/img/tooltag-add.svg": "admin/img/tooltag-add.e59d620a9742.svg", "admin/img/inline-delete.svg": "admin/img/inline-delete.fec1b761f254.svg", "admin/img/LICENSE": "admin/img/LICENSE.2c54f4e1ca1c", "admin/img/icon-changelink.svg": "admin/img/icon-changelink.18d2fd706348.svg", "admin/img/icon-unknown.svg": "admin/img/icon-unknown.a18cb4398978.svg", "admin/img/sorting-icons.svg": "admin/img/sorting-icons.3a097b59f104.svg", "admin/img/icon-viewlink.svg": "admin/img/icon-viewlink.41eb31f7826e.svg", "admin/img/icon-yes.svg": "admin/img/icon-yes.d2f9f035226a.svg", "admin/img/icon-addlink.svg": "admin/img/icon-addlink.d519b3bab011.svg", "admin/img/icon-unknown-alt.svg": "admin/img/icon-unknown-alt.81536e128bb6.svg", "admin/img/icon-deletelink.svg": "admin/img/icon-deletelink.564ef9dc3854.svg", "admin/img/README.txt": "admin/img/README.a70711a38d87.txt", "admin/img/selector-icons.svg": "admin/img/selector-icons.b4555096cea2.svg", "admin/img/calendar-icons.svg": "admin/img/calendar-icons.39b290681a8b.svg", "admin/img/tooltag-arrowright.svg": "admin/img/tooltag-arrowright.bbfb788a849e.svg", "admin/img/icon-alert.svg": "admin/img/icon-alert.034cc7d8a67f.svg", "admin/fonts/Roboto-Light-webfont.woff": "admin/fonts/Roboto-Light-webfont.c73eb1ceba33.woff", "admin/fonts/Roboto-Bold-webfont.woff": "admin/fonts/Roboto-Bold-webfont.50d75e48e0a3.woff", "admin/fonts/Roboto-Regular-webfont.woff": "admin/fonts/Roboto-Regular-webfont.35b07eb2f871.woff", "admin/fonts/README.txt": "admin/fonts/README.ab99e6b541ea.txt", "admin/fonts/LICENSE.txt": "admin/fonts/LICENSE.d273d63619c9.txt", "colorfield/jscolor/jscolor.min.js": "colorfield/jscolor/jscolor.min.a95f47b9b32a.js", "colorfield/jscolor/jscolor.js": "colorfield/jscolor/jscolor.7d21b45432c0.js", "3d_assets/hotel/model.json": "3d_assets/hotel/model.51a6dff87eeb.json", "3d_assets/tiles/8.png": "3d_assets/tiles/8.bbd1240ae615.png", "3d_assets/tiles/9.png": "3d_assets/tiles/9.537893ab6075.png", "3d_assets/tiles/14.png": "3d_assets/tiles/14.c294b8354273.png", "3d_assets/tiles/28.png": "3d_assets/tiles/28.c28909e8edfa.png", "3d_assets/tiles/29.png": "3d_assets/tiles/29.260e921c31d2.png", "3d_assets/tiles/15.png": "3d_assets/tiles/15.aa666a0c0b6b.png", "3d_assets/tiles/17.png": "3d_assets/tiles/17.aa28ce3ddd25.png", "3d_assets/tiles/16.png": "3d_assets/tiles/16.9df89a5003dd.png", "3d_assets/tiles/12.png": "3d_assets/tiles/12.336448665bed.png", "3d_assets/tiles/13.png": "3d_assets/tiles/13.cc07ce3113fd.png", "3d_assets/tiles/39.png": "3d_assets/tiles/39.4b5bb3a6cd5c.png", "3d_assets/tiles/11.png": "3d_assets/tiles/11.35b20f65ff09.png", "3d_assets/tiles/10.png": "3d_assets/tiles/10.68bfa3350e1c.png", "3d_assets/tiles/38.png": "3d_assets/tiles/38.de5bb0207a65.png", "3d_assets/tiles/35.png": "3d_assets/tiles/35.3f2dbf37ffb4.png", "3d_assets/tiles/21.png": "3d_assets/tiles/21.b1b78c0d81d2.png", "3d_assets/tiles/20.png": "3d_assets/tiles/20.62f2d60c3fd3.png", "3d_assets/tiles/34.png": "3d_assets/tiles/34.5ba90defca55.png", "3d_assets/tiles/22.png": "3d_assets/tiles/22.d69a9bb6ee64.png", "3d_assets/tiles/36.png": "3d_assets/tiles/36.11121369a3d4.png", "3d_assets/tiles/37.png": "3d_assets/tiles/37.7298f39ea173.png", "3d_assets/tiles/23.png": "3d_assets/tiles/23.cc91266f3d74.png", "3d_assets/tiles/27.png": "3d_assets/tiles/27.7aa88d556c5f.png", "3d_assets/tiles/33.png": "3d_assets/tiles/33.9b7a32913679.png", "3d_assets/tiles/32.png": "3d_assets/tiles/32.bdaec08fcd0b.png", "3d_assets/tiles/26.png": "3d_assets/tiles/26.43a720d7296a.png", "3d_assets/tiles/18.png": "3d_assets/tiles/18.ceef24a081d6.png", "3d_assets/tiles/30.png": "3d_assets/tiles/30.64cc1e467b03.png", "3d_assets/tiles/24.png": "3d_assets/tiles/24.9f7db848df22.png", "3d_assets/tiles/25.png": "3d_assets/tiles/25.4dff953eaced.png", "3d_assets/tiles/31.png": "3d_assets/tiles/31.8fa59a8c8f56.png", "3d_assets/tiles/19.png": "3d_assets/tiles/19.3828cd5e4eae.png", "3d_assets/tiles/4.png": "3d_assets/tiles/4.8ad48ab6496f.png", "3d_assets/tiles/5.png": "3d_assets/tiles/5.7298fa2889a9.png", "3d_assets/tiles/-1.png": "3d_assets/tiles/-1.506d5e77f694.png", "3d_assets/tiles/7.png": "3d_assets/tiles/7.cbc37fd717ac.png", "3d_assets/tiles/6.png": "3d_assets/tiles/6.81b77c10cf80.png", "3d_assets/tiles/2.png": "3d_assets/tiles/2.b5b349d6163b.png", "3d_assets/tiles/3.png": "3d_assets/tiles/3.d8049143ad9d.png", "3d_assets/tiles/1.png": "3d_assets/tiles/1.7ff787525fe0.png", "3d_assets/tiles/0.png": "3d_assets/tiles/0.ae4a2fd33e48.png", "3d_assets/house/model.json": "3d_assets/house/model.03b421b0a47b.json", "blockly/blocks/test_blocks.js": "blockly/blocks/test_blocks.6b52ca3b681d.js", "blockly/blocks/variables.js": "blockly/blocks/variables.081381074c23.js", "blockly/blocks/logic.js": "blockly/blocks/logic.9c02fb4e2d1f.js", "blockly/blocks/lists.js": "blockly/blocks/lists.74ab356654ce.js", "blockly/blocks/variables_dynamic.js": "blockly/blocks/variables_dynamic.16bfc0e4f635.js", "blockly/blocks/procedures.js": "blockly/blocks/procedures.2eaa2c84d816.js", "blockly/blocks/math.js": "blockly/blocks/math.408b3ab237ae.js", "blockly/blocks/colour.js": "blockly/blocks/colour.a8f4bb0ba8cf.js", "blockly/blocks/loops.js": "blockly/blocks/loops.d627a7bf21b9.js", "blockly/blocks/text.js": "blockly/blocks/text.39fb615a2ce8.js", "blockly/core/constants.js": "blockly/core/constants.e7337a728578.js", "blockly/core/shortcut_registry.js": "blockly/core/shortcut_registry.3fc5818f08b4.js", "blockly/core/flyout_horizontal.js": "blockly/core/flyout_horizontal.c0dbe4013e61.js", "blockly/core/workspace_dragger.js": "blockly/core/workspace_dragger.83d003f2a59b.js", "blockly/core/touch_gesture.js": "blockly/core/touch_gesture.3e99ebca441d.js", "blockly/core/positionable_test.js": "blockly/core/positionable_test.72f615e3ea25.js", "blockly/core/shortcut_items.js": "blockly/core/shortcut_items.8bda2aea3952.js", "blockly/core/field_textinput.js": "blockly/core/field_textinput.04bce964729a.js", "blockly/core/input_types.js": "blockly/core/input_types.3da120001fb8.js", "blockly/core/registry.js": "blockly/core/registry.85406feac0dc.js", "blockly/core/variables.js": "blockly/core/variables.065de189e46b.js", "blockly/core/dropdowndiv.js": "blockly/core/dropdowndiv.8738ccf8e5eb.js", "blockly/core/delete_area.js": "blockly/core/delete_area.4add424bbc93.js", "blockly/core/insertion_marker_manager.js": "blockly/core/insertion_marker_manager.684adbf31982.js", "blockly/core/field_variable.js": "blockly/core/field_variable.2b5506e84907.js", "blockly/core/field_angle.js": "blockly/core/field_angle.7dcfd6e717a9.js", "blockly/core/workspace_comment_svg.js": "blockly/core/workspace_comment_svg.91939fb842d2.js", "blockly/core/tooltip.js": "blockly/core/tooltip.31a167ed0010.js", "blockly/core/mutator.js": "blockly/core/mutator.629370d27580.js", "blockly/core/warning.js": "blockly/core/warning.0f32ad66a206.js", "blockly/core/variable_map.js": "blockly/core/variable_map.a4f9d4a4c537.js", "blockly/core/xml.js": "blockly/core/xml.4fbbb097f9f9.js", "blockly/core/connection_types.js": "blockly/core/connection_types.152a19e8eee0.js", "blockly/core/block_svg.js": "blockly/core/block_svg.be8f38be0be1.js", "blockly/core/workspace_svg.js": "blockly/core/workspace_svg.0358294f4cb8.js", "blockly/core/connection_db.js": "blockly/core/connection_db.566c89e79da0.js", "blockly/core/field_multilineinput.js": "blockly/core/field_multilineinput.955cd019942d.js", "blockly/core/workspace_comment.js": "blockly/core/workspace_comment.a4b8e319dfa9.js", "blockly/core/grid.js": "blockly/core/grid.7eaf4edb21c0.js", "blockly/core/workspace_audio.js": "blockly/core/workspace_audio.474111980a1e.js", "blockly/core/flyout_dragger.js": "blockly/core/flyout_dragger.04c4fd5792e6.js", "blockly/core/options.js": "blockly/core/options.83c95eb0a703.js", "blockly/core/field.js": "blockly/core/field.362489474f12.js", "blockly/core/bubble_dragger.js": "blockly/core/bubble_dragger.833368bf25ba.js", "blockly/core/icon.js": "blockly/core/icon.d96758a59bba.js", "blockly/core/field_checkbox.js": "blockly/core/field_checkbox.53183bc55f0a.js", "blockly/core/metrics_manager.js": "blockly/core/metrics_manager.67ee8bff0471.js", "blockly/core/field_number.js": "blockly/core/field_number.42a52819dc12.js", "blockly/core/theme.js": "blockly/core/theme.4f46e18f8f1f.js", "blockly/core/requires.js": "blockly/core/requires.23c331842e24.js", "blockly/core/field_label_serializable.js": "blockly/core/field_label_serializable.50aac87491fa.js", "blockly/core/field_dropdown.js": "blockly/core/field_dropdown.4b4c27a23a91.js", "blockly/core/browser_events.js": "blockly/core/browser_events.3a16c2550146.js", "blockly/core/gesture.js": "blockly/core/gesture.3fcc31307344.js", "blockly/core/comment.js": "blockly/core/comment.1f81f84c97b5.js", "blockly/core/field_image.js": "blockly/core/field_image.37e251c35201.js", "blockly/core/variables_dynamic.js": "blockly/core/variables_dynamic.c99353f36099.js", "blockly/core/msg.js": "blockly/core/msg.b56e01b1b751.js", "blockly/core/contextmenu_items.js": "blockly/core/contextmenu_items.0bad78be1891.js", "blockly/core/blockly.js": "blockly/core/blockly.2f3d95300969.js", "blockly/core/blocks.js": "blockly/core/blocks.bbd0486f5961.js", "blockly/core/theme_manager.js": "blockly/core/theme_manager.637930609f26.js", "blockly/core/procedures.js": "blockly/core/procedures.2c5ac306a0bc.js", "blockly/core/block.js": "blockly/core/block.a4735e0a8118.js", "blockly/core/workspace.js": "blockly/core/workspace.035efc39ba40.js", "blockly/core/positionable_helpers.js": "blockly/core/positionable_helpers.c6d840efe048.js", "blockly/core/contextmenu.js": "blockly/core/contextmenu.60e7cc902ae7.js", "blockly/core/scrollbar.js": "blockly/core/scrollbar.b7557191ed06.js", "blockly/core/plugin_manager.js": "blockly/core/plugin_manager.057ef679a192.js", "blockly/core/trashcan.js": "blockly/core/trashcan.4a97e55dda32.js", "blockly/core/variable_model.js": "blockly/core/variable_model.747f44808b1d.js", "blockly/core/flyout_base.js": "blockly/core/flyout_base.d5e3b75fc433.js", "blockly/core/component_manager.js": "blockly/core/component_manager.6ff723f2878f.js", "blockly/core/flyout_vertical.js": "blockly/core/flyout_vertical.de7155ef6bc9.js", "blockly/core/widgetdiv.js": "blockly/core/widgetdiv.d5fd39c35553.js", "blockly/core/zoom_controls.js": "blockly/core/zoom_controls.1fac2060b9e1.js", "blockly/core/field_label.js": "blockly/core/field_label.6c923b614b6f.js", "blockly/core/block_drag_surface.js": "blockly/core/block_drag_surface.5c83a0796868.js", "blockly/core/utils.js": "blockly/core/utils.48ac0c767b84.js", "blockly/core/menuitem.js": "blockly/core/menuitem.04b7cc72aa9b.js", "blockly/core/inject.js": "blockly/core/inject.53b3f324aa6c.js", "blockly/core/workspace_comment_render_svg.js": "blockly/core/workspace_comment_render_svg.5ca74d37e65e.js", "blockly/core/generator.js": "blockly/core/generator.30389afdf23c.js", "blockly/core/extensions.js": "blockly/core/extensions.142790b10dd4.js", "blockly/core/menu.js": "blockly/core/menu.180c49071fad.js", "blockly/core/css.js": "blockly/core/css.0688f1e0bf4f.js", "blockly/core/field_colour.js": "blockly/core/field_colour.324531a3e8b7.js", "blockly/core/connection.js": "blockly/core/connection.17804bad655c.js", "blockly/core/flyout_button.js": "blockly/core/flyout_button.30e69a4d668f.js", "blockly/core/drag_target.js": "blockly/core/drag_target.56034260236d.js", "blockly/core/names.js": "blockly/core/names.f9db4625b5b0.js", "blockly/core/block_animations.js": "blockly/core/block_animations.0811144dec3d.js", "blockly/core/marker_manager.js": "blockly/core/marker_manager.72f91b8025a4.js", "blockly/core/block_dragger.js": "blockly/core/block_dragger.90fbc4714bf2.js", "blockly/core/connection_checker.js": "blockly/core/connection_checker.db484f39d8d3.js", "blockly/core/rendered_connection.js": "blockly/core/rendered_connection.1ec3608d63ca.js", "blockly/core/field_registry.js": "blockly/core/field_registry.917f16403412.js", "blockly/core/touch.js": "blockly/core/touch.42fd41da9535.js", "blockly/core/input.js": "blockly/core/input.81b2b248e279.js", "blockly/core/workspace_drag_surface_svg.js": "blockly/core/workspace_drag_surface_svg.67ece7250497.js", "blockly/core/bubble.js": "blockly/core/bubble.706f836cc126.js", "blockly/core/contextmenu_registry.js": "blockly/core/contextmenu_registry.7bac2617ec1a.js", "blockly/msg/zh-hant.js": "blockly/msg/zh-hant.4b98a00e1b54.js", "blockly/msg/sr-latn.js": "blockly/msg/sr-latn.18ce57df7b39.js", "blockly/msg/pt.js": "blockly/msg/pt.1a742afe163a.js", "blockly/msg/constants.d.ts": "blockly/msg/constants.d.ab0050431bea.ts", "blockly/msg/bcc.d.ts": "blockly/msg/bcc.d.3635eca430ad.ts", "blockly/msg/hy.d.ts": "blockly/msg/hy.d.c6414cde4dce.ts", "blockly/msg/ug-arab.js": "blockly/msg/ug-arab.d379d138ed5a.js", "blockly/msg/sl.d.ts": "blockly/msg/sl.d.ec0a1778cd55.ts", "blockly/msg/mk.d.ts": "blockly/msg/mk.d.02e55d7cc5ef.ts", "blockly/msg/tr.d.ts": "blockly/msg/tr.d.0c4f3bd10ad1.ts", "blockly/msg/vi.js": "blockly/msg/vi.410234e7a8c4.js", "blockly/msg/lv.js": "blockly/msg/lv.b25673e998e8.js", "blockly/msg/lki.js": "blockly/msg/lki.7051a8cc84ff.js", "blockly/msg/gl.js": "blockly/msg/gl.3316c02fb3b0.js", "blockly/msg/pl.js": "blockly/msg/pl.846bec070c05.js", "blockly/msg/ee.d.ts": "blockly/msg/ee.d.e43f75fb061d.ts", "blockly/msg/is.d.ts": "blockly/msg/is.d.cb66a305775f.ts", "blockly/msg/el.js": "blockly/msg/el.070db6990c8c.js", "blockly/msg/lt.d.ts": "blockly/msg/lt.d.a666ad0d1946.ts", "blockly/msg/hu.d.ts": "blockly/msg/hu.d.077c651a27a2.ts", "blockly/msg/pms.d.ts": "blockly/msg/pms.d.90eb71a3cb1d.ts", "blockly/msg/et.js": "blockly/msg/et.322a485714d2.js", "blockly/msg/is.js": "blockly/msg/is.4fce42963f44.js", "blockly/msg/sl.js": "blockly/msg/sl.a07fd79a6ef2.js", "blockly/msg/bn.d.ts": "blockly/msg/bn.d.e7b762fb3f95.ts", "blockly/msg/ko.js": "blockly/msg/ko.f9f880429182.js", "blockly/msg/ms.js": "blockly/msg/ms.bb76f6ae9a3f.js", "blockly/msg/yo.d.ts": "blockly/msg/yo.d.a976e038c30a.ts", "blockly/msg/fi.js": "blockly/msg/fi.269afe290023.js", "blockly/msg/th.js": "blockly/msg/th.b01c552a08e8.js", "blockly/msg/ig.d.ts": "blockly/msg/ig.d.d09478859aab.ts", "blockly/msg/ha.d.ts": "blockly/msg/ha.d.53be3e1fa31c.ts", "blockly/msg/ms.d.ts": "blockly/msg/ms.d.9b992317a1f7.ts", "blockly/msg/ru.js": "blockly/msg/ru.aafb00badbd3.js", "blockly/msg/nl.d.ts": "blockly/msg/nl.d.719dc8d71c19.ts", "blockly/msg/eu.js": "blockly/msg/eu.394575807007.js", "blockly/msg/mk.js": "blockly/msg/mk.90ca9ceb6b49.js", "blockly/msg/yo.js": "blockly/msg/yo.a8c24b4c1892.js", "blockly/msg/kn.js": "blockly/msg/kn.1ac0624e8f64.js", "blockly/msg/sq.js": "blockly/msg/sq.4927d1d57515.js", "blockly/msg/lo.js": "blockly/msg/lo.81c3c71d136a.js", "blockly/msg/tlh.js": "blockly/msg/tlh.e00280923efc.js", "blockly/msg/zgh.js": "blockly/msg/zgh.a52a47226c2a.js", "blockly/msg/tl.js": "blockly/msg/tl.a9928b8140b1.js", "blockly/msg/mnw.d.ts": "blockly/msg/mnw.d.fcdd33a6cde0.ts", "blockly/msg/ja.d.ts": "blockly/msg/ja.d.83c2e3d8c871.ts", "blockly/msg/qqq.d.ts": "blockly/msg/qqq.d.ee86433b4e67.ts", "blockly/msg/uk.d.ts": "blockly/msg/uk.d.2ac218924042.ts", "blockly/msg/ru.d.ts": "blockly/msg/ru.d.c4e2c5876e76.ts", "blockly/msg/pl.d.ts": "blockly/msg/pl.d.14ef0f537411.ts", "blockly/msg/ab.d.ts": "blockly/msg/ab.d.a100987a7ea4.ts", "blockly/msg/de.d.ts": "blockly/msg/de.d.4feed7d94daa.ts", "blockly/msg/be-tarask.js": "blockly/msg/be-tarask.af8511e0f958.js", "blockly/msg/ja.js": "blockly/msg/ja.ce95e455ba18.js", "blockly/msg/he.js": "blockly/msg/he.5b5b8508296a.js", "blockly/msg/fi.d.ts": "blockly/msg/fi.d.13b189e093c3.ts", "blockly/msg/bg.js": "blockly/msg/bg.b4b4ec1a5ac2.js", "blockly/msg/dty.d.ts": "blockly/msg/dty.d.52ff2b3477e4.ts", "blockly/msg/pms.js": "blockly/msg/pms.cd4070177a3a.js", "blockly/msg/zgh.d.ts": "blockly/msg/zgh.d.8c541f717b9b.ts", "blockly/msg/eo.d.ts": "blockly/msg/eo.d.b7a95ba81694.ts", "blockly/msg/hrx.d.ts": "blockly/msg/hrx.d.591bcc0998af.ts", "blockly/msg/hy.js": "blockly/msg/hy.0b3c7a78886f.js", "blockly/msg/ta.d.ts": "blockly/msg/ta.d.ecc29cd8395e.ts", "blockly/msg/ia.js": "blockly/msg/ia.7eacaa22a24a.js", "blockly/msg/ha.js": "blockly/msg/ha.cb0eb095e28b.js", "blockly/msg/bcc.js": "blockly/msg/bcc.3a5a854fea14.js", "blockly/msg/shn.d.ts": "blockly/msg/shn.d.18ba9c225943.ts", "blockly/msg/ur.d.ts": "blockly/msg/ur.d.496ad3a487f3.ts", "blockly/msg/be.d.ts": "blockly/msg/be.d.e50be270fc63.ts", "blockly/msg/pt.d.ts": "blockly/msg/pt.d.d7cb17e350e0.ts", "blockly/msg/az.d.ts": "blockly/msg/az.d.81f3cba071f9.ts", "blockly/msg/sk.d.ts": "blockly/msg/sk.d.80cb1a7afd3c.ts", "blockly/msg/en.d.ts": "blockly/msg/en.d.cef0c58fd223.ts", "blockly/msg/ia.d.ts": "blockly/msg/ia.d.ec9da61d94ee.ts", "blockly/msg/id.js": "blockly/msg/id.4bf5d66e3478.js", "blockly/msg/az.js": "blockly/msg/az.2d953d3ec31c.js", "blockly/msg/skr-arab.d.ts": "blockly/msg/skr-arab.d.ed2886f12ef5.ts", "blockly/msg/tl.d.ts": "blockly/msg/tl.d.c8a0d6392753.ts", "blockly/msg/tcy.js": "blockly/msg/tcy.d262e86f066e.js", "blockly/msg/ab.js": "blockly/msg/ab.688941273da4.js", "blockly/msg/sc.js": "blockly/msg/sc.7b1cae94ba70.js", "blockly/msg/xmf.js": "blockly/msg/xmf.5244e51ba2f5.js", "blockly/msg/sr.d.ts": "blockly/msg/sr.d.3f0f2d2f669c.ts", "blockly/msg/xmf.d.ts": "blockly/msg/xmf.d.559f69b6932a.ts", "blockly/msg/it.d.ts": "blockly/msg/it.d.b2032e4a0cd6.ts", "blockly/msg/et.d.ts": "blockly/msg/et.d.5866c33acad4.ts", "blockly/msg/sd.d.ts": "blockly/msg/sd.d.61bb262b57ec.ts", "blockly/msg/lb.js": "blockly/msg/lb.65ca4088e8d3.js", "blockly/msg/ca.js": "blockly/msg/ca.46250fa81f7a.js", "blockly/msg/ta.js": "blockly/msg/ta.93e212b66d42.js", "blockly/msg/ba.js": "blockly/msg/ba.2695594803d8.js", "blockly/msg/sd.js": "blockly/msg/sd.366670847619.js", "blockly/msg/sq.d.ts": "blockly/msg/sq.d.f26eb49635a0.ts", "blockly/msg/kn.d.ts": "blockly/msg/kn.d.e805bbc08aba.ts", "blockly/msg/diq.js": "blockly/msg/diq.456d2b217d39.js", "blockly/msg/sr-latn.d.ts": "blockly/msg/sr-latn.d.49b83ad31061.ts", "blockly/msg/ig.js": "blockly/msg/ig.5897ab78d596.js", "blockly/msg/te.js": "blockly/msg/te.90775a070cec.js", "blockly/msg/fr.d.ts": "blockly/msg/fr.d.ed5965830fd2.ts", "blockly/msg/nb.js": "blockly/msg/nb.26b2fdc01ea3.js", "blockly/msg/oc.d.ts": "blockly/msg/oc.d.31090f381512.ts", "blockly/msg/be.js": "blockly/msg/be.aa30aa8f74d0.js", "blockly/msg/zh-hans.d.ts": "blockly/msg/zh-hans.d.afb4bebac8f9.ts", "blockly/msg/gor.d.ts": "blockly/msg/gor.d.02637595c546.ts", "blockly/msg/gor.js": "blockly/msg/gor.7d582ba215f5.js", "blockly/msg/el.d.ts": "blockly/msg/el.d.21ec7c7f613c.ts", "blockly/msg/pt-br.js": "blockly/msg/pt-br.f2900b82161b.js", "blockly/msg/br.d.ts": "blockly/msg/br.d.57a10fa461a2.ts", "blockly/msg/shn.js": "blockly/msg/shn.5b66d3bdab4a.js", "blockly/msg/oc.js": "blockly/msg/oc.404953e1f93e.js", "blockly/msg/ug-arab.d.ts": "blockly/msg/ug-arab.d.6364fdae4acb.ts", "blockly/msg/lrc.js": "blockly/msg/lrc.05c569d94e45.js", "blockly/msg/da.js": "blockly/msg/da.e56421eab8cc.js", "blockly/msg/ca.d.ts": "blockly/msg/ca.d.5d0901a70cc5.ts", "blockly/msg/skr-arab.js": "blockly/msg/skr-arab.5b541cf0ca46.js", "blockly/msg/hi.d.ts": "blockly/msg/hi.d.6393c62ed23c.ts", "blockly/msg/ro.d.ts": "blockly/msg/ro.d.03911d010abe.ts", "blockly/msg/bg.d.ts": "blockly/msg/bg.d.889e4b9373d9.ts", "blockly/msg/ko.d.ts": "blockly/msg/ko.d.5a734e7b45b1.ts", "blockly/msg/lki.d.ts": "blockly/msg/lki.d.2e1a1d337e8b.ts", "blockly/msg/ee.js": "blockly/msg/ee.861598684cc7.js", "blockly/msg/pt-br.d.ts": "blockly/msg/pt-br.d.ef54478f58cf.ts", "blockly/msg/be-tarask.d.ts": "blockly/msg/be-tarask.d.243b480761c9.ts", "blockly/msg/fa.js": "blockly/msg/fa.53139c06a99c.js", "blockly/msg/de.js": "blockly/msg/de.41dce8a14e7a.js", "blockly/msg/he.d.ts": "blockly/msg/he.d.b7ac8952772a.ts", "blockly/msg/eu.d.ts": "blockly/msg/eu.d.d30e7e7d5730.ts", "blockly/msg/gl.d.ts": "blockly/msg/gl.d.b927253b3fa3.ts", "blockly/msg/msg.d.ts": "blockly/msg/msg.d.4c8706e7c42b.ts", "blockly/msg/en.js": "blockly/msg/en.e677d1d0a620.js", "blockly/msg/lo.d.ts": "blockly/msg/lo.d.6ad1db0297a3.ts", "blockly/msg/bs.js": "blockly/msg/bs.de74b4d091d8.js", "blockly/msg/sv.js": "blockly/msg/sv.c687f11337fd.js", "blockly/msg/fa.d.ts": "blockly/msg/fa.d.24cfb297dc67.ts", "blockly/msg/vi.d.ts": "blockly/msg/vi.d.0b39c4422638.ts", "blockly/msg/kab.js": "blockly/msg/kab.3c2c82b2da71.js", "blockly/msg/te.d.ts": "blockly/msg/te.d.94fb5deae4e1.ts", "blockly/msg/cs.d.ts": "blockly/msg/cs.d.28319b1d893b.ts", "blockly/msg/hi.js": "blockly/msg/hi.346fe7538541.js", "blockly/msg/uk.js": "blockly/msg/uk.e385f465adc1.js", "blockly/msg/mnw.js": "blockly/msg/mnw.8f330b6c6ae4.js", "blockly/msg/cs.js": "blockly/msg/cs.3151a6a7765b.js", "blockly/msg/fr.js": "blockly/msg/fr.4929552caf38.js", "blockly/msg/nl.js": "blockly/msg/nl.e7ce51824fb3.js", "blockly/msg/en-gb.js": "blockly/msg/en-gb.c84fcaaca15f.js", "blockly/msg/sr.js": "blockly/msg/sr.cf8b79aeb483.js", "blockly/msg/hu.js": "blockly/msg/hu.1f1bef9bada1.js", "blockly/msg/id.d.ts": "blockly/msg/id.d.5212246f51b3.ts", "blockly/msg/dty.js": "blockly/msg/dty.1a23c91d71c6.js", "blockly/msg/tcy.d.ts": "blockly/msg/tcy.d.013c7e9e61f3.ts", "blockly/msg/hrx.js": "blockly/msg/hrx.7c23213c5fd4.js", "blockly/msg/kab.d.ts": "blockly/msg/kab.d.5ef2b52682f2.ts", "blockly/msg/da.d.ts": "blockly/msg/da.d.5ed01ff0d7e9.ts", "blockly/msg/lt.js": "blockly/msg/lt.93109740dff9.js", "blockly/msg/lv.d.ts": "blockly/msg/lv.d.8fc66f0d09e2.ts", "blockly/msg/ar.js": "blockly/msg/ar.6c665376c255.js", "blockly/msg/sv.d.ts": "blockly/msg/sv.d.4ecda326f495.ts", "blockly/msg/en-gb.d.ts": "blockly/msg/en-gb.d.5bbef2186473.ts", "blockly/msg/th.d.ts": "blockly/msg/th.d.1b93376e3d1c.ts", "blockly/msg/diq.d.ts": "blockly/msg/diq.d.14a47ac622d4.ts", "blockly/msg/ar.d.ts": "blockly/msg/ar.d.d75e59d823ea.ts", "blockly/msg/sc.d.ts": "blockly/msg/sc.d.57b63beeb640.ts", "blockly/msg/lrc.d.ts": "blockly/msg/lrc.d.e52eb0e486f3.ts", "blockly/msg/es.d.ts": "blockly/msg/es.d.a5368a93af6a.ts", "blockly/msg/sk.js": "blockly/msg/sk.549380ae4f18.js", "blockly/msg/it.js": "blockly/msg/it.6f2851b9c4a9.js", "blockly/msg/lb.d.ts": "blockly/msg/lb.d.721b3411a12f.ts", "blockly/msg/es.js": "blockly/msg/es.14b08c4d9898.js", "blockly/msg/bn.js": "blockly/msg/bn.dac29e5bf2d0.js", "blockly/msg/eo.js": "blockly/msg/eo.4474cb05e217.js", "blockly/msg/ro.js": "blockly/msg/ro.ff3a4f8161e2.js", "blockly/msg/tlh.d.ts": "blockly/msg/tlh.d.49c832a59a1c.ts", "blockly/msg/ur.js": "blockly/msg/ur.1534ff7bd084.js", "blockly/msg/br.js": "blockly/msg/br.871cb6c62ac3.js", "blockly/msg/zh-hans.js": "blockly/msg/zh-hans.721e7de12610.js", "blockly/msg/nb.d.ts": "blockly/msg/nb.d.ff984f99d4e0.ts", "blockly/msg/synonyms.d.ts": "blockly/msg/synonyms.d.b2202d61dc33.ts", "blockly/msg/zh-hant.d.ts": "blockly/msg/zh-hant.d.1b5b54981eb9.ts", "blockly/msg/tr.js": "blockly/msg/tr.274e8e2b29a7.js", "blockly/msg/ba.d.ts": "blockly/msg/ba.d.546e1677d0e0.ts", "blockly/generators/dart.js": "blockly/generators/dart.68161cd7a3f8.js", "blockly/generators/lua.js": "blockly/generators/lua.a9f510af11f4.js", "blockly/generators/javascript.js": "blockly/generators/javascript.c4e7267e68f3.js", "blockly/generators/php.js": "blockly/generators/php.59be72a12949.js", "blockly/generators/python.js": "blockly/generators/python.adfcf830f3a1.js", "blockly/media/disconnect.wav": "blockly/media/disconnect.409e7fabb73e.wav", "blockly/media/disconnect.ogg": "blockly/media/disconnect.f43c7533d7d9.ogg", "blockly/media/pilcrow.png": "blockly/media/pilcrow.580e99d437cb.png", "blockly/media/click.mp3": "blockly/media/click.217b91bbdfcb.mp3", "blockly/media/handopen.cur": "blockly/media/handopen.505cbb975d61.cur", "blockly/media/handdelete.cur": "blockly/media/handdelete.b0b4b0b44ed0.cur", "blockly/media/delete.mp3": "blockly/media/delete.dfe58781f568.mp3", "blockly/media/disconnect.mp3": "blockly/media/disconnect.a275b1ba174f.mp3", "blockly/media/quote1.png": "blockly/media/quote1.390e15501d3d.png", "blockly/media/quote0.png": "blockly/media/quote0.0b9354e0d3e2.png", "blockly/media/1x1.gif": "blockly/media/1x1.4b252c2abb05.gif", "blockly/media/sprites.svg": "blockly/media/sprites.911d25e52cb1.svg", "blockly/media/handclosed.cur": "blockly/media/handclosed.6b45ea439228.cur", "blockly/media/click.wav": "blockly/media/click.2ca099226956.wav", "blockly/media/delete.ogg": "blockly/media/delete.5c3387d5bcbe.ogg", "blockly/media/sprites.png": "blockly/media/sprites.e48f11399017.png", "blockly/media/delete.wav": "blockly/media/delete.ace3b1f0042c.wav", "blockly/media/dropdown-arrow.svg": "blockly/media/dropdown-arrow.be850da55269.svg", "blockly/media/click.ogg": "blockly/media/click.d62ab7f0a6c2.ogg", "sound/se/04_shock02.wav": "sound/se/04_shock02.40858494c342.wav", "sound/se/05_whistle03.wav": "sound/se/05_whistle03.d9d4c6cac0d8.wav", "sound/se/hover.mp3": "sound/se/hover.42abd1b23d13.mp3", "sound/se/cash.mp3": "sound/se/cash.942e460d4489.mp3", "sound/se/04_down02.wav": "sound/se/04_down02.eabc77953674.wav", "sound/se/02_decide.wav": "sound/se/02_decide.e7421bcac686.wav", "sound/se/Coin.mp3": "sound/se/Coin.970d0ad370ca.mp3", "sound/se/ran_town_001.mp3": "sound/se/ran_town_001.bc2262991725.mp3", "sound/se/dice.mp3": "sound/se/dice.c91fe8d81d03.mp3", "sound/se/03_down01.wav": "sound/se/03_down01.455686245c2a.wav", "sound/se/02_bell02.wav": "sound/se/02_bell02.23f1078c3239.wav", "sound/se/turnover.mp3": "sound/se/turnover.011eb1c60a50.mp3", "sound/se/01_up01.wav": "sound/se/01_up01.a204600226c0.wav", "sound/se/03_chime03.wav": "sound/se/03_chime03.5d0258801ecc.wav", "sound/se/game_win.wav": "sound/se/game_win.dab292cd3997.wav", "sound/se/teleport_1.mp3": "sound/se/teleport_1.ab8178ff45f7.mp3", "sound/se/move.mp3": "sound/se/move.87a67c06ff8a.mp3", "sound/se/01_bell01.wav": "sound/se/01_bell01.1e4d3a6109b9.wav", "sound/se/01_fly01.wav": "sound/se/01_fly01.cbcd6f2bcf99.wav", "sound/se/01_chime01.wav": "sound/se/01_chime01.3dd7e3d71f60.wav", "sound/se/02_tozyo.wav": "sound/se/02_tozyo.788993c49fe2.wav", "sound/se/03_whistle01.wav": "sound/se/03_whistle01.50f1ae3f22e1.wav", "sound/se/02_up02.wav": "sound/se/02_up02.2aca6b17e946.wav", "sound/se/03_shock01.wav": "sound/se/03_shock01.a43b1301683f.wav", "sound/se/04_whistle02.wav": "sound/se/04_whistle02.5f23096d6189.wav", "sound/se/build.mp3": "sound/se/build.b1ad64646d5e.mp3", "sound/bgm/score_board_bgm_1.ogg": "sound/bgm/score_board_bgm_1.065fc8a0edfb.ogg", "sound/bgm/score_board_bgm_0.mp3": "sound/bgm/score_board_bgm_0.4e3d63b26a96.mp3", "sound/bgm/background.mp3": "sound/bgm/background.4893460b4a8e.mp3", "css/styles.css": "css/styles.a78e62da5997.css", "css/card_create.css": "css/card_create.257721c8d2d2.css", "css/join.css": "css/join.dbecebaee445.css", "css/login.css": "css/login.1a572b73f446.css", "css/map_score_board.css": "css/map_score_board.bc0aa65b3f66.css", "css/game.css": "css/game.6c2dc2f45ef7.css", "css/main.css": "css/main.7943a184415d.css", "css/music_list.css": "css/music_list.b3dcdaac76fb.css", "css/w3.css": "css/w3.ba0537e95747.css", "css/creator_cardset_detail.css": "css/creator_cardset_detail.f8486f077562.css", "css/rolling_dice.css": "css/rolling_dice.12fd3f572d93.css", "css/creator_map.css": "css/creator_map.4f675cce6fd5.css", "css/profile.css": "css/profile.75637cd0df96.css", "images/default_avatar.png": "images/default_avatar.42b9115fc456.png", "images/hotel.png": "images/hotel.7b89920d96ad.png", "images/player_0.png": "images/player_0.a91d60ab3eff.png", "images/scoreboard_bg.png": "images/scoreboard_bg.a98d0d5e8610.png", "images/player_1.png": "images/player_1.5d84ce5dcfdf.png", "images/player_3.png": "images/player_3.8abc10b7ba2e.png", "images/player_2.png": "images/player_2.193bf11ad539.png", "images/player_1_mark.png": "images/player_1_mark.ce00fc8a64c9.png", "images/player_0_mark.png": "images/player_0_mark.e9e612d52bc0.png", "images/switch-camera.svg": "images/switch-camera.b80987b08bf8.svg", "images/house.png": "images/house.0782abfd96cc.png", "images/background.jpg": "images/background.a6ff02893010.jpg", "images/favicon.png": "images/favicon.6f4a1ead0a67.png", "images/chat.png": "images/chat.3ce910ebf88a.png", "images/player_2_mark.png": "images/player_2_mark.be10d50abf2d.png", "images/player_3_mark.png": "images/player_3_mark.331184af5f0b.png", "colorfield/colorfield.js": "colorfield/colorfield.264e315223be.js", "3d_assets/board.js": "3d_assets/board.6dd36c41d17d.js", "3d_assets/scene.gltf": "3d_assets/scene.1108c265d782.gltf", "3d_assets/ground.png": "3d_assets/ground.700303c8b354.png", "3d_assets/board_texture.jpg": "3d_assets/board_texture.9e9e0475b5bb.jpg", "3d_assets/board.obj": "3d_assets/board.c0241610738e.obj", "blockly/blockly.d.ts": "blockly/blockly.d.f503c21381c3.ts", "blockly/dart_compressed.js.map": "blockly/dart_compressed.js.6016ee36dc76.map", "blockly/php_compressed.js.map": "blockly/php_compressed.js.4bc72675624b.map", "blockly/dart.js": "blockly/dart.220a7097b2b2.js", "blockly/core.js": "blockly/core.4366d18eca2e.js", "blockly/javascript_compressed.js.map": "blockly/javascript_compressed.js.375e77fcca7d.map", "blockly/blocks.d.ts": "blockly/blocks.d.f3263ed86816.ts", "blockly/lua.d.ts": "blockly/lua.d.753453cfe4cc.ts", "blockly/lua_compressed.js": "blockly/lua_compressed.532bdba6f380.js", "blockly/lua.js": "blockly/lua.7c775a529ca5.js", "blockly/javascript_compressed.js": "blockly/javascript_compressed.93f073eaacaa.js", "blockly/blocks_compressed.js": "blockly/blocks_compressed.81bd3bb18d2e.js", "blockly/dart_compressed.js": "blockly/dart_compressed.88900b65c3a0.js", "blockly/blockly_compressed.js": "blockly/blockly_compressed.409ae5883f6e.js", "blockly/index.js": "blockly/index.6df68d57f128.js", "blockly/lua_compressed.js.map": "blockly/lua_compressed.js.4b1c9d591136.map", "blockly/README.md": "blockly/README.4a26d753bd4e.md", "blockly/php.d.ts": "blockly/php.d.49f32ef12b3b.ts", "blockly/javascript.js": "blockly/javascript.bb3265e727e5.js", "blockly/blockly.min.js": "blockly/blockly.min.a3719d9e9296.js", "blockly/blockly.js": "blockly/blockly.d2d4de37a841.js", "blockly/blocks.js": "blockly/blocks.41a1921d7fd6.js", "blockly/core.d.ts": "blockly/core.d.a2ee1bfdcbed.ts", "blockly/node.js": "blockly/node.1659f30264d4.js", "blockly/php.js": "blockly/php.850542ee7e72.js", "blockly/package.json": "blockly/package.49369c058329.json", "blockly/core-browser.js": "blockly/core-browser.c3c7fe44db63.js", "blockly/dart.d.ts": "blockly/dart.d.d0416441a5ef.ts", "blockly/javascript.d.ts": "blockly/javascript.d.2ee5f7f88314.ts", "blockly/php_compressed.js": "blockly/php_compressed.069db6a36070.js", "blockly/index.d.ts": "blockly/index.d.9fea5032598c.ts", "blockly/python_compressed.js.map": "blockly/python_compressed.js.09e2b0987e80.map", "blockly/blockly_compressed.js.map": "blockly/blockly_compressed.js.c9473b2eb6cc.map", "blockly/browser.js": "blockly/browser.024f95bd6a38.js", "blockly/python_compressed.js": "blockly/python_compressed.58195d531d46.js", "blockly/python.d.ts": "blockly/python.d.aa369a6d254a.ts", "blockly/python.js": "blockly/python.db9a435fdbf4.js", "blockly/blocks_compressed.js.map": "blockly/blocks_compressed.js.58e6042f0c46.map"}, "version": "1.0"}